remclient/__init__.py
remclient/constants.py
remclient/remclient.py
remclient-1.1.2.data/scripts/rem-tool
remclient-1.1.2.dist-info/METADATA
remclient-1.1.2.dist-info/WHEEL
remclient-1.1.2.dist-info/top_level.txt
remclient-1.1.2.dist-info/RECORD
